otlmow_visuals/PyVisWrapper.py
otlmow_visuals-1.0.dist-info/licenses/LICENSE
otlmow_visuals-1.0.dist-info/METADATA
otlmow_visuals-1.0.dist-info/WHEEL
otlmow_visuals-1.0.dist-info/top_level.txt
otlmow_visuals-1.0.dist-info/RECORD
